tronpropy/__init__.py
tronpropy/main.py
tronpropy-0.1.0.dist-info/LICENSE.txt
tronpropy-0.1.0.dist-info/METADATA
tronpropy-0.1.0.dist-info/WHEEL
tronpropy-0.1.0.dist-info/top_level.txt
tronpropy-0.1.0.dist-info/RECORD
