Metadata-Version: 2.2
Name: tronpropy
Version: 0.1.0
Summary: tronpropy library for Python
Author: etjueK
License-File: LICENSE.txt
Dynamic: author
Dynamic: description
Dynamic: description-content-type
Dynamic: summary
